alist.py
alistpy-1.2.0.dist-info/LICENSE.md
alistpy-1.2.0.dist-info/METADATA
alistpy-1.2.0.dist-info/WHEEL
alistpy-1.2.0.dist-info/top_level.txt
alistpy-1.2.0.dist-info/RECORD
