Metadata-Version: 2.1
Name: alistpy
Version: 1.2.0
Summary: An Association List construct
Home-page: https://git.sr.ht/~shakna/alistpy
Author: James Milne
Author-email: james.milne@protonmail.com
License: UNKNOWN
Platform: UNKNOWN
Classifier: Programming Language :: Python :: 3
Classifier: License :: OSI Approved :: BSD License
Classifier: Operating System :: OS Independent
